CHANGES.rst
LICENSE.txt
MANIFEST.in
README.rst
setup.cfg
setup.py
capmoe/__init__.py
capmoe.egg-info/PKG-INFO
capmoe.egg-info/SOURCES.txt
capmoe.egg-info/dependency_links.txt
capmoe.egg-info/requires.txt
capmoe.egg-info/top_level.txt
capmoe/api/__init__.py
capmoe/cv/__init__.py
capmoe/cv/capdetector.py
test/test_api.py