Metadata-Version: 1.1
Name: capmoe
Version: 0.0.3
Summary: CapMoe - Cap Beer cap image search, CV algorithms and their API
Home-page: https://github.com/laysakura/capmoe
Author: Sho Nakatani
Author-email: lay.sakura@gmail.com
License: LICENSE.txt
Platform: UNKNOWN
Classifier: Programming Language :: Python
Classifier: Development Status :: 4 - Beta
Classifier: Programming Language :: Python :: 2.7
Classifier: Operating System :: POSIX :: Linux
